[
{"num":0.000,"ele":243.4},
{"num":0.617,"ele":250.7},
{"num":1.073,"ele":250.6},
{"num":1.577,"ele":252.7},
{"num":2.065,"ele":258.2},
{"num":2.350,"ele":265.9},
{"num":2.626,"ele":286.0},
{"num":2.914,"ele":311.8},
{"num":3.237,"ele":331.5},
{"num":3.452,"ele":348.9},
{"num":3.756,"ele":371.2},
{"num":4.149,"ele":400.1},
{"num":4.503,"ele":428.1},
{"num":4.878,"ele":459.0},
{"num":5.182,"ele":490.8},
{"num":5.625,"ele":527.2},
{"num":6.095,"ele":562.3},
{"num":6.399,"ele":593.8},
{"num":7.072,"ele":636.3},
{"num":7.571,"ele":658.8},
{"num":7.894,"ele":665.3},
{"num":8.361,"ele":673.3},
{"num":8.732,"ele":686.2},
{"num":9.205,"ele":699.4},
{"num":9.680,"ele":719.1},
{"num":10.250,"ele":753.2},
{"num":10.652,"ele":758.7},
{"num":11.156,"ele":770.8},
{"num":11.664,"ele":801.6},
{"num":11.994,"ele":823.9},
{"num":12.268,"ele":850.7},
{"num":12.680,"ele":886.5},
{"num":13.226,"ele":930.1},
{"num":13.552,"ele":962.3},
{"num":13.879,"ele":954.5},
{"num":14.625,"ele":894.6},
{"num":14.868,"ele":841.8},
{"num":15.520,"ele":774.8},
{"num":15.899,"ele":733.7},
{"num":16.344,"ele":687.1},
{"num":17.118,"ele":650.1},
{"num":17.368,"ele":630.1},
{"num":18.006,"ele":595.0},
{"num":18.611,"ele":562.1},
{"num":18.986,"ele":521.4},
{"num":19.378,"ele":473.9},
{"num":19.772,"ele":427.6},
{"num":20.034,"ele":378.3},
{"num":20.830,"ele":314.7},
{"num":21.342,"ele":263.6},
{"num":21.661,"ele":255.7},
{"num":22.180,"ele":259.1},
{"num":22.700,"ele":275.3},
{"num":23.057,"ele":292.8},
{"num":23.304,"ele":273.2},
{"num":23.932,"ele":251.3},
{"num":24.491,"ele":252.9},
{"num":25.005,"ele":250.4},
{"num":25.341,"ele":250.1},
{"num":26.056,"ele":241.7},
{"num":26.554,"ele":225.3},
{"num":27.293,"ele":231.6},
{"num":27.514,"ele":248.9},
{"num":27.984,"ele":268.8},
{"num":28.265,"ele":288.8},
{"num":28.829,"ele":318.8},
{"num":29.146,"ele":323.0},
{"num":29.545,"ele":325.9},
{"num":29.866,"ele":334.2},
{"num":30.324,"ele":329.0},
{"num":30.750,"ele":330.0},
{"num":31.372,"ele":342.4},
{"num":31.791,"ele":320.4},
{"num":32.181,"ele":295.7},
{"num":32.425,"ele":283.1},
{"num":32.815,"ele":277.9},
{"num":33.266,"ele":276.9},
{"num":33.598,"ele":285.1},
{"num":34.068,"ele":290.6},
{"num":34.549,"ele":304.6},
{"num":34.836,"ele":309.5},
{"num":35.464,"ele":304.0},
{"num":35.771,"ele":306.6},
{"num":36.138,"ele":314.0},
{"num":36.725,"ele":329.2},
{"num":37.348,"ele":340.4},
{"num":37.931,"ele":352.6},
{"num":38.398,"ele":362.8},
{"num":38.872,"ele":377.9},
{"num":39.594,"ele":397.5},
{"num":40.125,"ele":416.7},
{"num":40.555,"ele":441.0},
{"num":41.063,"ele":475.2},
{"num":41.348,"ele":505.8},
{"num":41.679,"ele":542.4},
{"num":42.179,"ele":598.9},
{"num":42.702,"ele":607.3},
{"num":43.238,"ele":579.6},
{"num":43.872,"ele":581.1},
{"num":44.458,"ele":588.5},
{"num":44.900,"ele":602.8},
{"num":45.452,"ele":636.9},
{"num":45.938,"ele":644.7},
{"num":46.389,"ele":643.7},
{"num":47.213,"ele":653.4},
{"num":47.798,"ele":671.4},
{"num":48.631,"ele":695.8},
{"num":48.913,"ele":713.7},
{"num":49.186,"ele":720.9},
{"num":49.577,"ele":741.1},
{"num":50.112,"ele":742.1},
{"num":50.849,"ele":779.9},
{"num":51.501,"ele":830.9},
{"num":51.935,"ele":869.3},
{"num":52.236,"ele":910.0},
{"num":52.794,"ele":942.7},
{"num":53.426,"ele":916.5},
{"num":53.933,"ele":893.3},
{"num":54.460,"ele":874.8},
{"num":55.804,"ele":877.9},
{"num":56.226,"ele":901.2},
{"num":56.643,"ele":905.9},
{"num":57.313,"ele":912.4},
{"num":57.677,"ele":911.8},
{"num":58.249,"ele":900.3},
{"num":59.082,"ele":908.8},
{"num":60.098,"ele":922.5},
{"num":60.574,"ele":932.9},
{"num":61.023,"ele":939.4},
{"num":61.543,"ele":944.7}
]